{"corr": -0.02971137537983953, "p": 0.69313913751832867, "rgb": "#677a7e", "ncc_corr": -0.040096174585617185, "words": [{"color": "#44f794", "text": "juice", "initloc": {"y": 0, "x": 0}, "size": 8}, {"color": "#3bff7a", "text": "powdered", "initloc": {"y": 0, "x": 0}, "size": 7}, {"color": "#0aff57", "text": "variety", "initloc": {"y": 0, "x": 0}, "size": 7}, {"color": "#51929e", "text": "different", "initloc": {"y": 0, "x": 0}, "size": 7}, {"color": "#4eff88", "text": "lemon", "initloc": {"y": 0, "x": 0}, "size": 7}, {"color": "#36e994", "text": "types", "initloc": {"y": 0, "x": 0}, "size": 7}, {"color": "#8d7f8e", "text": "priori", "initloc": {"y": 0, "x": 0}, "size": 7}, {"color": "#53e66f", "text": "cabbage", "initloc": {"y": 0, "x": 0}, "size": 6}, {"color": "#879d4c", "text": "ophthalmologist", "initloc": {"y": 0, "x": 0}, "size": 6}, {"color": "#29ffba", "text": "mix", "initloc": {"y": 0, "x": 0}, "size": 6}, {"color": "#3bb17c", "text": "cooking", "initloc": {"y": 0, "x": 0}, "size": 6}, {"color": "#58d42f", "text": "sacs", "initloc": {"y": 0, "x": 0}, "size": 6}, {"color": "#57d36d", "text": "vegetables", "initloc": {"y": 0, "x": 0}, "size": 6}, {"color": "#53d56e", "text": "cakes", "initloc": {"y": 0, "x": 0}, "size": 6}, {"color": "#1eb829", "text": "various", "initloc": {"y": 0, "x": 0}, "size": 6}, {"color": "#739f71", "text": "dv", "initloc": {"y": 0, "x": 0}, "size": 6}, {"color": "#7a1a9e", "text": "study", "initloc": {"y": 0, "x": 0}, "size": 6}, {"color": "#62a1bc", "text": "kinds", "initloc": {"y": 0, "x": 0}, "size": 6}, {"color": "#59fca3", "text": "boiled", "initloc": {"y": 0, "x": 0}, "size": 6}, {"color": "#59e4c0", "text": "boil", "initloc": {"y": 0, "x": 0}, "size": 6}], "cb": 0, "zyx": [6, 34, 64]}