{"corr": 0.0022855670903721083, "p": 0.48451651323782113, "rgb": "#816d7d", "ncc_corr": -0.026122641420204359, "words": [{"color": "#625c26", "text": "meals", "initloc": {"y": 0, "x": 0}, "size": 16}, {"color": "#74f829", "text": "pounds", "initloc": {"y": 0, "x": 0}, "size": 13}, {"color": "#572726", "text": "trips", "initloc": {"y": 0, "x": 0}, "size": 12}, {"color": "#a80052", "text": "staying", "initloc": {"y": 0, "x": 0}, "size": 11}, {"color": "#789244", "text": "food", "initloc": {"y": 0, "x": 0}, "size": 11}, {"color": "#4fbe5c", "text": "washing", "initloc": {"y": 0, "x": 0}, "size": 11}, {"color": "#95001a", "text": "spent", "initloc": {"y": 0, "x": 0}, "size": 10}, {"color": "#40174c", "text": "hour", "initloc": {"y": 0, "x": 0}, "size": 10}, {"color": "#7f6d51", "text": "meal", "initloc": {"y": 0, "x": 0}, "size": 10}, {"color": "#3bb17c", "text": "cooking", "initloc": {"y": 0, "x": 0}, "size": 10}, {"color": "#4d0043", "text": "hours", "initloc": {"y": 0, "x": 0}, "size": 10}, {"color": "#476462", "text": "comfortably", "initloc": {"y": 0, "x": 0}, "size": 10}, {"color": "#666f57", "text": "cleaned", "initloc": {"y": 0, "x": 0}, "size": 9}, {"color": "#ba0073", "text": "slept", "initloc": {"y": 0, "x": 0}, "size": 9}, {"color": "#671c00", "text": "week", "initloc": {"y": 0, "x": 0}, "size": 9}, {"color": "#893e2a", "text": "dine", "initloc": {"y": 0, "x": 0}, "size": 9}, {"color": "#9d1e2f", "text": "dinner", "initloc": {"y": 0, "x": 0}, "size": 9}, {"color": "#83df4a", "text": "weighed", "initloc": {"y": 0, "x": 0}, "size": 9}, {"color": "#2c0e5b", "text": "nights", "initloc": {"y": 0, "x": 0}, "size": 9}, {"color": "#5c7e40", "text": "cleaning", "initloc": {"y": 0, "x": 0}, "size": 9}], "cb": 0, "zyx": [19, 33, 55]}