{"corr": -0.088124316922657736, "p": 0.93315875099448897, "rgb": "#6c6f80", "ncc_corr": -0.17027176385805023, "words": [{"color": "#b959cc", "text": "aw", "initloc": {"y": 0, "x": 0}, "size": 5}, {"color": "#8560c2", "text": "newfound", "initloc": {"y": 0, "x": 0}, "size": 5}, {"color": "#3d9861", "text": "bathing", "initloc": {"y": 0, "x": 0}, "size": 5}, {"color": "#820096", "text": "sometime", "initloc": {"y": 0, "x": 0}, "size": 5}, {"color": "#990032", "text": "visiting", "initloc": {"y": 0, "x": 0}, "size": 5}, {"color": "#af002d", "text": "visit", "initloc": {"y": 0, "x": 0}, "size": 5}, {"color": "#9d913d", "text": "diapers", "initloc": {"y": 0, "x": 0}, "size": 5}, {"color": "#438d47", "text": "bath", "initloc": {"y": 0, "x": 0}, "size": 4}, {"color": "#678e0c", "text": "fitch", "initloc": {"y": 0, "x": 0}, "size": 4}, {"color": "#4271bb", "text": "yoga", "initloc": {"y": 0, "x": 0}, "size": 4}, {"color": "#7a8e16", "text": "lingerie", "initloc": {"y": 0, "x": 0}, "size": 4}, {"color": "#55d053", "text": "bikinis", "initloc": {"y": 0, "x": 0}, "size": 4}, {"color": "#65af24", "text": "abercrombie", "initloc": {"y": 0, "x": 0}, "size": 4}, {"color": "#5d4aaa", "text": "everyday", "initloc": {"y": 0, "x": 0}, "size": 4}, {"color": "#9433a1", "text": "bringing", "initloc": {"y": 0, "x": 0}, "size": 4}, {"color": "#c403ab", "text": "troubles", "initloc": {"y": 0, "x": 0}, "size": 4}, {"color": "#4a7e0e", "text": "bakery", "initloc": {"y": 0, "x": 0}, "size": 4}, {"color": "#974a1b", "text": "hostess", "initloc": {"y": 0, "x": 0}, "size": 4}, {"color": "#926250", "text": "lena", "initloc": {"y": 0, "x": 0}, "size": 4}, {"color": "#6253ac", "text": "helped", "initloc": {"y": 0, "x": 0}, "size": 4}], "cb": 0, "zyx": [21, 62, 40]}