{"corr": 0.11952110105691779, "p": 0.020804449689421571, "rgb": "#6546a2", "ncc_corr": 0.20289087070381412, "words": [{"color": "#41667f", "text": "convenient", "initloc": {"y": 0, "x": 0}, "size": 13}, {"color": "#559754", "text": "contents", "initloc": {"y": 0, "x": 0}, "size": 12}, {"color": "#6e8ab2", "text": "waste", "initloc": {"y": 0, "x": 0}, "size": 9}, {"color": "#97575d", "text": "ordering", "initloc": {"y": 0, "x": 0}, "size": 9}, {"color": "#af1c95", "text": "expectation", "initloc": {"y": 0, "x": 0}, "size": 9}, {"color": "#23c19b", "text": "vacuum", "initloc": {"y": 0, "x": 0}, "size": 8}, {"color": "#b36ac6", "text": "people's", "initloc": {"y": 0, "x": 0}, "size": 8}, {"color": "#728f89", "text": "disposal", "initloc": {"y": 0, "x": 0}, "size": 8}, {"color": "#1fa55e", "text": "fill", "initloc": {"y": 0, "x": 0}, "size": 8}, {"color": "#8b3083", "text": "information", "initloc": {"y": 0, "x": 0}, "size": 8}, {"color": "#73812e", "text": "liquor", "initloc": {"y": 0, "x": 0}, "size": 8}, {"color": "#5a6818", "text": "customers", "initloc": {"y": 0, "x": 0}, "size": 7}, {"color": "#bf3984", "text": "foreigners", "initloc": {"y": 0, "x": 0}, "size": 7}, {"color": "#609998", "text": "solution", "initloc": {"y": 0, "x": 0}, "size": 7}, {"color": "#858878", "text": "cigarettes", "initloc": {"y": 0, "x": 0}, "size": 7}, {"color": "#567c00", "text": "purchase", "initloc": {"y": 0, "x": 0}, "size": 7}, {"color": "#d73094", "text": "personal", "initloc": {"y": 0, "x": 0}, "size": 7}, {"color": "#37a44e", "text": "packet", "initloc": {"y": 0, "x": 0}, "size": 7}, {"color": "#3a6952", "text": "empty", "initloc": {"y": 0, "x": 0}, "size": 7}, {"color": "#4195c3", "text": "simplest", "initloc": {"y": 0, "x": 0}, "size": 7}], "cb": 0, "zyx": [10, 88, 64]}