{"corr": 0.082894382553940119, "p": 0.079208665958034802, "rgb": "#7f7b9d", "ncc_corr": 0.1862010029740199, "words": [{"color": "#81aa46", "text": "carried", "initloc": {"y": 0, "x": 0}, "size": 8}, {"color": "#74dd5e", "text": "horse", "initloc": {"y": 0, "x": 0}, "size": 7}, {"color": "#ba765c", "text": "captured", "initloc": {"y": 0, "x": 0}, "size": 7}, {"color": "#93c629", "text": "carrying", "initloc": {"y": 0, "x": 0}, "size": 6}, {"color": "#6e81b0", "text": "treacherous", "initloc": {"y": 0, "x": 0}, "size": 6}, {"color": "#e17e70", "text": "captive", "initloc": {"y": 0, "x": 0}, "size": 6}, {"color": "#883c5e", "text": "voyage", "initloc": {"y": 0, "x": 0}, "size": 6}, {"color": "#de465e", "text": "rescued", "initloc": {"y": 0, "x": 0}, "size": 5}, {"color": "#eb6759", "text": "wounded", "initloc": {"y": 0, "x": 0}, "size": 5}, {"color": "#887543", "text": "ashore", "initloc": {"y": 0, "x": 0}, "size": 5}, {"color": "#b11394", "text": "unable", "initloc": {"y": 0, "x": 0}, "size": 5}, {"color": "#ff487d", "text": "attacked", "initloc": {"y": 0, "x": 0}, "size": 5}, {"color": "#e266a8", "text": "attack", "initloc": {"y": 0, "x": 0}, "size": 5}, {"color": "#8f5347", "text": "expedition", "initloc": {"y": 0, "x": 0}, "size": 5}, {"color": "#99c453", "text": "carry", "initloc": {"y": 0, "x": 0}, "size": 5}, {"color": "#b75b66", "text": "rescue", "initloc": {"y": 0, "x": 0}, "size": 5}, {"color": "#29cf68", "text": "aloft", "initloc": {"y": 0, "x": 0}, "size": 5}, {"color": "#36683c", "text": "boat", "initloc": {"y": 0, "x": 0}, "size": 5}, {"color": "#00fd9c", "text": "heavy", "initloc": {"y": 0, "x": 0}, "size": 5}, {"color": "#c700cd", "text": "relieved", "initloc": {"y": 0, "x": 0}, "size": 4}], "cb": 0, "zyx": [7, 65, 62]}