{"corr": 0.048097318015549527, "p": 0.20684405323455979, "rgb": "#63647f", "ncc_corr": 0.12700141202670326, "words": [{"color": "#8b3083", "text": "information", "initloc": {"y": 0, "x": 0}, "size": 16}, {"color": "#158e98", "text": "technology", "initloc": {"y": 0, "x": 0}, "size": 14}, {"color": "#6b46ed", "text": "science", "initloc": {"y": 0, "x": 0}, "size": 13}, {"color": "#08926b", "text": "digital", "initloc": {"y": 0, "x": 0}, "size": 12}, {"color": "#656ba2", "text": "research", "initloc": {"y": 0, "x": 0}, "size": 12}, {"color": "#332152", "text": "computer", "initloc": {"y": 0, "x": 0}, "size": 11}, {"color": "#d21f59", "text": "report", "initloc": {"y": 0, "x": 0}, "size": 11}, {"color": "#bb70cd", "text": "article", "initloc": {"y": 0, "x": 0}, "size": 11}, {"color": "#608fae", "text": "analysis", "initloc": {"y": 0, "x": 0}, "size": 11}, {"color": "#3a7490", "text": "nasa", "initloc": {"y": 0, "x": 0}, "size": 10}, {"color": "#688fdf", "text": "experiment", "initloc": {"y": 0, "x": 0}, "size": 10}, {"color": "#0ba273", "text": "electronic", "initloc": {"y": 0, "x": 0}, "size": 10}, {"color": "#8461f2", "text": "scientific", "initloc": {"y": 0, "x": 0}, "size": 9}, {"color": "#4d7e78", "text": "application", "initloc": {"y": 0, "x": 0}, "size": 9}, {"color": "#40897b", "text": "scanning", "initloc": {"y": 0, "x": 0}, "size": 9}, {"color": "#658ed0", "text": "experiments", "initloc": {"y": 0, "x": 0}, "size": 9}, {"color": "#7a1a9e", "text": "study", "initloc": {"y": 0, "x": 0}, "size": 9}, {"color": "#ac5677", "text": "general", "initloc": {"y": 0, "x": 0}, "size": 9}, {"color": "#516a49", "text": "pages", "initloc": {"y": 0, "x": 0}, "size": 9}, {"color": "#81496b", "text": "page", "initloc": {"y": 0, "x": 0}, "size": 9}], "cb": 0, "zyx": [9, 82, 32]}