{"corr": 0.19210979495845035, "p": 0.00049425729790312449, "rgb": "#822aba", "ncc_corr": 0.4073261462964472, "words": [{"color": "#8141b5", "text": "um", "initloc": {"y": 0, "x": 0}, "size": 17}, {"color": "#9258c8", "text": "giggled", "initloc": {"y": 0, "x": 0}, "size": 15}, {"color": "#b92fff", "text": "sounded", "initloc": {"y": 0, "x": 0}, "size": 14}, {"color": "#7f08c6", "text": "stumbled", "initloc": {"y": 0, "x": 0}, "size": 14}, {"color": "#ec0069", "text": "overheard", "initloc": {"y": 0, "x": 0}, "size": 13}, {"color": "#d12fda", "text": "laughed", "initloc": {"y": 0, "x": 0}, "size": 13}, {"color": "#7e5a4c", "text": "picked", "initloc": {"y": 0, "x": 0}, "size": 12}, {"color": "#a84ad6", "text": "liked", "initloc": {"y": 0, "x": 0}, "size": 12}, {"color": "#d74dff", "text": "confused", "initloc": {"y": 0, "x": 0}, "size": 12}, {"color": "#9f6ed1", "text": "reminds", "initloc": {"y": 0, "x": 0}, "size": 12}, {"color": "#ce0794", "text": "politely", "initloc": {"y": 0, "x": 0}, "size": 11}, {"color": "#ad30f0", "text": "reminded", "initloc": {"y": 0, "x": 0}, "size": 11}, {"color": "#9a4f67", "text": "found", "initloc": {"y": 0, "x": 0}, "size": 11}, {"color": "#a80a4f", "text": "roommate", "initloc": {"y": 0, "x": 0}, "size": 11}, {"color": "#5882a9", "text": "favorite", "initloc": {"y": 0, "x": 0}, "size": 11}, {"color": "#de45b9", "text": "madam", "initloc": {"y": 0, "x": 0}, "size": 11}, {"color": "#980f9e", "text": "find", "initloc": {"y": 0, "x": 0}, "size": 11}, {"color": "#ff025b", "text": "aunt", "initloc": {"y": 0, "x": 0}, "size": 11}, {"color": "#bc1dd0", "text": "chuckled", "initloc": {"y": 0, "x": 0}, "size": 10}, {"color": "#e20060", "text": "asked", "initloc": {"y": 0, "x": 0}, "size": 10}], "cb": 2, "zyx": [20, 28, 40]}