{"corr": 0.050465045055356074, "p": 0.19552614086108092, "rgb": "#877d98", "ncc_corr": 0.11818778520120665, "words": [{"color": "#429595", "text": "fall", "initloc": {"y": 0, "x": 0}, "size": 11}, {"color": "#794add", "text": "sudden", "initloc": {"y": 0, "x": 0}, "size": 9}, {"color": "#6f61c1", "text": "abrupt", "initloc": {"y": 0, "x": 0}, "size": 9}, {"color": "#4a9479", "text": "cliff", "initloc": {"y": 0, "x": 0}, "size": 9}, {"color": "#472aa1", "text": "approaching", "initloc": {"y": 0, "x": 0}, "size": 8}, {"color": "#28bca8", "text": "rise", "initloc": {"y": 0, "x": 0}, "size": 8}, {"color": "#00908f", "text": "winds", "initloc": {"y": 0, "x": 0}, "size": 7}, {"color": "#2cb485", "text": "slope", "initloc": {"y": 0, "x": 0}, "size": 7}, {"color": "#165a5a", "text": "hike", "initloc": {"y": 0, "x": 0}, "size": 7}, {"color": "#448056", "text": "landing", "initloc": {"y": 0, "x": 0}, "size": 7}, {"color": "#3e393b", "text": "ride", "initloc": {"y": 0, "x": 0}, "size": 7}, {"color": "#3e7b79", "text": "downhill", "initloc": {"y": 0, "x": 0}, "size": 7}, {"color": "#36683c", "text": "boat", "initloc": {"y": 0, "x": 0}, "size": 7}, {"color": "#3fbd65", "text": "falls", "initloc": {"y": 0, "x": 0}, "size": 7}, {"color": "#359192", "text": "plunge", "initloc": {"y": 0, "x": 0}, "size": 7}, {"color": "#00c04e", "text": "peak", "initloc": {"y": 0, "x": 0}, "size": 6}, {"color": "#4d3d1d", "text": "event", "initloc": {"y": 0, "x": 0}, "size": 6}, {"color": "#2f6483", "text": "storm", "initloc": {"y": 0, "x": 0}, "size": 6}, {"color": "#15bb91", "text": "rises", "initloc": {"y": 0, "x": 0}, "size": 6}, {"color": "#775588", "text": "begins", "initloc": {"y": 0, "x": 0}, "size": 6}], "cb": 0, "zyx": [6, 41, 51]}