{"corr": -0.043351916798689182, "p": 0.76934508957595638, "rgb": "#859486", "ncc_corr": -0.10379576383955698, "words": [{"color": "#66bc85", "text": "pulling", "initloc": {"y": 0, "x": 0}, "size": 5}, {"color": "#a3a0ff", "text": "tone", "initloc": {"y": 0, "x": 0}, "size": 5}, {"color": "#808297", "text": "steer", "initloc": {"y": 0, "x": 0}, "size": 5}, {"color": "#49b8c9", "text": "pulse", "initloc": {"y": 0, "x": 0}, "size": 4}, {"color": "#4cf1d5", "text": "twisting", "initloc": {"y": 0, "x": 0}, "size": 4}, {"color": "#52ff8d", "text": "weight", "initloc": {"y": 0, "x": 0}, "size": 4}, {"color": "#c0cad9", "text": "gut", "initloc": {"y": 0, "x": 0}, "size": 4}, {"color": "#7cfba9", "text": "teeth", "initloc": {"y": 0, "x": 0}, "size": 4}, {"color": "#1fdf4b", "text": "wheel", "initloc": {"y": 0, "x": 0}, "size": 4}, {"color": "#80fc97", "text": "tooth", "initloc": {"y": 0, "x": 0}, "size": 4}, {"color": "#7bcaff", "text": "sensitive", "initloc": {"y": 0, "x": 0}, "size": 3}, {"color": "#45ba8b", "text": "scratch", "initloc": {"y": 0, "x": 0}, "size": 3}, {"color": "#85b4ff", "text": "subtle", "initloc": {"y": 0, "x": 0}, "size": 3}, {"color": "#36b593", "text": "adjusting", "initloc": {"y": 0, "x": 0}, "size": 3}, {"color": "#55ff99", "text": "cutting", "initloc": {"y": 0, "x": 0}, "size": 3}, {"color": "#55e781", "text": "elbows", "initloc": {"y": 0, "x": 0}, "size": 3}, {"color": "#9fb6ff", "text": "healing", "initloc": {"y": 0, "x": 0}, "size": 3}, {"color": "#618ccd", "text": "popping", "initloc": {"y": 0, "x": 0}, "size": 3}, {"color": "#65bd7a", "text": "pull", "initloc": {"y": 0, "x": 0}, "size": 3}, {"color": "#797c82", "text": "picking", "initloc": {"y": 0, "x": 0}, "size": 3}], "cb": 0, "zyx": [5, 36, 63]}