{"corr": 0.16295187383008647, "p": 0.0026645691670213077, "rgb": "#775954", "ncc_corr": 0.42915649156734315, "words": [{"color": "#5c3f0c", "text": "homes", "initloc": {"y": 0, "x": 0}, "size": 30}, {"color": "#3f6400", "text": "local", "initloc": {"y": 0, "x": 0}, "size": 30}, {"color": "#577d1a", "text": "california", "initloc": {"y": 0, "x": 0}, "size": 29}, {"color": "#465000", "text": "residents", "initloc": {"y": 0, "x": 0}, "size": 29}, {"color": "#604e16", "text": "neighborhood", "initloc": {"y": 0, "x": 0}, "size": 27}, {"color": "#1d6626", "text": "tourist", "initloc": {"y": 0, "x": 0}, "size": 24}, {"color": "#106314", "text": "downtown", "initloc": {"y": 0, "x": 0}, "size": 24}, {"color": "#1c6200", "text": "visitors", "initloc": {"y": 0, "x": 0}, "size": 24}, {"color": "#565005", "text": "town", "initloc": {"y": 0, "x": 0}, "size": 24}, {"color": "#614400", "text": "service", "initloc": {"y": 0, "x": 0}, "size": 23}, {"color": "#31650e", "text": "nearby", "initloc": {"y": 0, "x": 0}, "size": 23}, {"color": "#3a5d4a", "text": "streets", "initloc": {"y": 0, "x": 0}, "size": 23}, {"color": "#7a3b4d", "text": "shelter", "initloc": {"y": 0, "x": 0}, "size": 23}, {"color": "#57615e", "text": "countryside", "initloc": {"y": 0, "x": 0}, "size": 22}, {"color": "#424d00", "text": "shopping", "initloc": {"y": 0, "x": 0}, "size": 22}, {"color": "#4c5603", "text": "services", "initloc": {"y": 0, "x": 0}, "size": 22}, {"color": "#8a0000", "text": "home", "initloc": {"y": 0, "x": 0}, "size": 22}, {"color": "#4a450e", "text": "airport", "initloc": {"y": 0, "x": 0}, "size": 22}, {"color": "#af002d", "text": "visit", "initloc": {"y": 0, "x": 0}, "size": 22}, {"color": "#3e6f00", "text": "street", "initloc": {"y": 0, "x": 0}, "size": 21}], "cb": 1, "zyx": [10, 71, 55]}