{"corr": 0.087007739721558508, "p": 0.069348344397594394, "rgb": "#987979", "ncc_corr": 0.2404680265581568, "words": [{"color": "#8d46f2", "text": "souls", "initloc": {"y": 0, "x": 0}, "size": 15}, {"color": "#835cf0", "text": "universe", "initloc": {"y": 0, "x": 0}, "size": 14}, {"color": "#5383ba", "text": "infinite", "initloc": {"y": 0, "x": 0}, "size": 13}, {"color": "#93b5f3", "text": "essence", "initloc": {"y": 0, "x": 0}, "size": 12}, {"color": "#74cd29", "text": "coin", "initloc": {"y": 0, "x": 0}, "size": 10}, {"color": "#b158d6", "text": "destiny", "initloc": {"y": 0, "x": 0}, "size": 9}, {"color": "#db84d5", "text": "thou", "initloc": {"y": 0, "x": 0}, "size": 9}, {"color": "#b854ff", "text": "eternal", "initloc": {"y": 0, "x": 0}, "size": 9}, {"color": "#559754", "text": "contents", "initloc": {"y": 0, "x": 0}, "size": 9}, {"color": "#ff4c5a", "text": "prisoner", "initloc": {"y": 0, "x": 0}, "size": 9}, {"color": "#65d311", "text": "coins", "initloc": {"y": 0, "x": 0}, "size": 9}, {"color": "#a06eed", "text": "mankind", "initloc": {"y": 0, "x": 0}, "size": 8}, {"color": "#6a75af", "text": "infinity", "initloc": {"y": 0, "x": 0}, "size": 8}, {"color": "#9b4ddb", "text": "realm", "initloc": {"y": 0, "x": 0}, "size": 8}, {"color": "#e359f5", "text": "curse", "initloc": {"y": 0, "x": 0}, "size": 8}, {"color": "#be75e0", "text": "unto", "initloc": {"y": 0, "x": 0}, "size": 8}, {"color": "#508fda", "text": "cosmic", "initloc": {"y": 0, "x": 0}, "size": 8}, {"color": "#9d2edb", "text": "existence", "initloc": {"y": 0, "x": 0}, "size": 8}, {"color": "#556ec0", "text": "worlds", "initloc": {"y": 0, "x": 0}, "size": 8}, {"color": "#c45bff", "text": "gods", "initloc": {"y": 0, "x": 0}, "size": 8}], "cb": 0, "zyx": [24, 55, 32]}