{"corr": -0.059882838455645675, "p": 0.84567097535207014, "rgb": "#877c78", "ncc_corr": -0.14928626855647703, "words": [{"color": "#4f577b", "text": "entire", "initloc": {"y": 0, "x": 0}, "size": 4}, {"color": "#977498", "text": "majority", "initloc": {"y": 0, "x": 0}, "size": 4}, {"color": "#b73dd4", "text": "debate", "initloc": {"y": 0, "x": 0}, "size": 4}, {"color": "#674295", "text": "occupy", "initloc": {"y": 0, "x": 0}, "size": 4}, {"color": "#818cc1", "text": "lies", "initloc": {"y": 0, "x": 0}, "size": 4}, {"color": "#20da59", "text": "portion", "initloc": {"y": 0, "x": 0}, "size": 4}, {"color": "#bb70cd", "text": "article", "initloc": {"y": 0, "x": 0}, "size": 3}, {"color": "#988de8", "text": "entirely", "initloc": {"y": 0, "x": 0}, "size": 3}, {"color": "#e45c5c", "text": "persons", "initloc": {"y": 0, "x": 0}, "size": 3}, {"color": "#d24ffe", "text": "lie", "initloc": {"y": 0, "x": 0}, "size": 3}, {"color": "#cc0c9c", "text": "post", "initloc": {"y": 0, "x": 0}, "size": 3}, {"color": "#52c9a0", "text": "broadly", "initloc": {"y": 0, "x": 0}, "size": 3}, {"color": "#826baa", "text": "examining", "initloc": {"y": 0, "x": 0}, "size": 3}, {"color": "#d36796", "text": "issue", "initloc": {"y": 0, "x": 0}, "size": 3}, {"color": "#8f5c4d", "text": "reserved", "initloc": {"y": 0, "x": 0}, "size": 3}, {"color": "#47f5a8", "text": "plain", "initloc": {"y": 0, "x": 0}, "size": 3}, {"color": "#c658a7", "text": "belong", "initloc": {"y": 0, "x": 0}, "size": 3}, {"color": "#cc57b8", "text": "lying", "initloc": {"y": 0, "x": 0}, "size": 3}, {"color": "#39964b", "text": "sprawled", "initloc": {"y": 0, "x": 0}, "size": 3}, {"color": "#6534b4", "text": "view", "initloc": {"y": 0, "x": 0}, "size": 3}], "cb": 0, "zyx": [6, 41, 37]}