{"corr": -0.024378388986718083, "p": 0.66061268019763064, "rgb": "#878082", "ncc_corr": -0.056887041548478894, "words": [{"color": "#4a7b38", "text": "repair", "initloc": {"y": 0, "x": 0}, "size": 19}, {"color": "#cc848c", "text": "risk", "initloc": {"y": 0, "x": 0}, "size": 18}, {"color": "#7b72ad", "text": "necessary", "initloc": {"y": 0, "x": 0}, "size": 18}, {"color": "#3d88c0", "text": "improve", "initloc": {"y": 0, "x": 0}, "size": 17}, {"color": "#aac59c", "text": "prevent", "initloc": {"y": 0, "x": 0}, "size": 16}, {"color": "#5f3575", "text": "task", "initloc": {"y": 0, "x": 0}, "size": 15}, {"color": "#9bc7aa", "text": "damage", "initloc": {"y": 0, "x": 0}, "size": 15}, {"color": "#b753a6", "text": "precautions", "initloc": {"y": 0, "x": 0}, "size": 15}, {"color": "#6766e3", "text": "difficult", "initloc": {"y": 0, "x": 0}, "size": 15}, {"color": "#c059a2", "text": "failure", "initloc": {"y": 0, "x": 0}, "size": 15}, {"color": "#896dc1", "text": "purpose", "initloc": {"y": 0, "x": 0}, "size": 14}, {"color": "#429f71", "text": "require", "initloc": {"y": 0, "x": 0}, "size": 14}, {"color": "#de86b0", "text": "treatment", "initloc": {"y": 0, "x": 0}, "size": 14}, {"color": "#3eb87e", "text": "requires", "initloc": {"y": 0, "x": 0}, "size": 14}, {"color": "#76407d", "text": "manage", "initloc": {"y": 0, "x": 0}, "size": 14}, {"color": "#6764bc", "text": "effort", "initloc": {"y": 0, "x": 0}, "size": 14}, {"color": "#7fbdcc", "text": "effective", "initloc": {"y": 0, "x": 0}, "size": 14}, {"color": "#82ef9f", "text": "removing", "initloc": {"y": 0, "x": 0}, "size": 14}, {"color": "#728f89", "text": "disposal", "initloc": {"y": 0, "x": 0}, "size": 14}, {"color": "#509297", "text": "maintain", "initloc": {"y": 0, "x": 0}, "size": 13}], "cb": 0, "zyx": [10, 74, 75]}