{"corr": 0.053638153222803749, "p": 0.18095894691745815, "rgb": "#b77497", "ncc_corr": 0.079384156790386615, "words": [{"color": "#b959cc", "text": "aw", "initloc": {"y": 0, "x": 0}, "size": 19}, {"color": "#ff5757", "text": "mothers", "initloc": {"y": 0, "x": 0}, "size": 15}, {"color": "#ff6ee1", "text": "jesus", "initloc": {"y": 0, "x": 0}, "size": 15}, {"color": "#ff3999", "text": "priest", "initloc": {"y": 0, "x": 0}, "size": 15}, {"color": "#ff4a9c", "text": "sarah", "initloc": {"y": 0, "x": 0}, "size": 14}, {"color": "#ff2e27", "text": "family", "initloc": {"y": 0, "x": 0}, "size": 14}, {"color": "#ff2b4e", "text": "daughter", "initloc": {"y": 0, "x": 0}, "size": 14}, {"color": "#7a67c4", "text": "sing", "initloc": {"y": 0, "x": 0}, "size": 14}, {"color": "#ff2945", "text": "children", "initloc": {"y": 0, "x": 0}, "size": 13}, {"color": "#b14dce", "text": "re", "initloc": {"y": 0, "x": 0}, "size": 13}, {"color": "#ff2d59", "text": "nephew", "initloc": {"y": 0, "x": 0}, "size": 12}, {"color": "#ff60a6", "text": "jew", "initloc": {"y": 0, "x": 0}, "size": 12}, {"color": "#ff3a80", "text": "child", "initloc": {"y": 0, "x": 0}, "size": 12}, {"color": "#ff346a", "text": "niece", "initloc": {"y": 0, "x": 0}, "size": 12}, {"color": "#9f5d84", "text": "english", "initloc": {"y": 0, "x": 0}, "size": 12}, {"color": "#ff2b7c", "text": "pregnant", "initloc": {"y": 0, "x": 0}, "size": 12}, {"color": "#ff488f", "text": "murder", "initloc": {"y": 0, "x": 0}, "size": 12}, {"color": "#c882a2", "text": "mama", "initloc": {"y": 0, "x": 0}, "size": 11}, {"color": "#ff2b5c", "text": "son", "initloc": {"y": 0, "x": 0}, "size": 11}, {"color": "#ff186e", "text": "mother", "initloc": {"y": 0, "x": 0}, "size": 11}], "cb": 0, "zyx": [25, 30, 45]}