{"corr": 0.02518293694755384, "p": 0.3343955977793997, "rgb": "#88bbc9", "ncc_corr": 0.045381795469145614, "words": [{"color": "#9cffde", "text": "flesh", "initloc": {"y": 0, "x": 0}, "size": 20}, {"color": "#a4b195", "text": "puts", "initloc": {"y": 0, "x": 0}, "size": 17}, {"color": "#69e8ca", "text": "touches", "initloc": {"y": 0, "x": 0}, "size": 16}, {"color": "#ef8fef", "text": "bodily", "initloc": {"y": 0, "x": 0}, "size": 16}, {"color": "#bb56fd", "text": "weep", "initloc": {"y": 0, "x": 0}, "size": 14}, {"color": "#6a95f0", "text": "thirst", "initloc": {"y": 0, "x": 0}, "size": 14}, {"color": "#c56afe", "text": "agony", "initloc": {"y": 0, "x": 0}, "size": 14}, {"color": "#8fa3c3", "text": "precious", "initloc": {"y": 0, "x": 0}, "size": 13}, {"color": "#93b5f3", "text": "essence", "initloc": {"y": 0, "x": 0}, "size": 13}, {"color": "#75be78", "text": "stripped", "initloc": {"y": 0, "x": 0}, "size": 13}, {"color": "#59ddf5", "text": "burning", "initloc": {"y": 0, "x": 0}, "size": 12}, {"color": "#e5aaff", "text": "vile", "initloc": {"y": 0, "x": 0}, "size": 12}, {"color": "#e175e7", "text": "sin", "initloc": {"y": 0, "x": 0}, "size": 12}, {"color": "#e4bfc1", "text": "man's", "initloc": {"y": 0, "x": 0}, "size": 12}, {"color": "#db7eb3", "text": "sacrificed", "initloc": {"y": 0, "x": 0}, "size": 12}, {"color": "#c376cf", "text": "thee", "initloc": {"y": 0, "x": 0}, "size": 11}, {"color": "#62c57b", "text": "spilling", "initloc": {"y": 0, "x": 0}, "size": 11}, {"color": "#82ef9f", "text": "removing", "initloc": {"y": 0, "x": 0}, "size": 11}, {"color": "#fc59e0", "text": "mercy", "initloc": {"y": 0, "x": 0}, "size": 11}, {"color": "#d5cde6", "text": "poison", "initloc": {"y": 0, "x": 0}, "size": 11}], "cb": 0, "zyx": [22, 54, 66]}