{"corr": -0.022556601956046411, "p": 0.64920663355675057, "rgb": "#c06c4a", "ncc_corr": -0.014157306366965465, "words": [{"color": "#d81e4e", "text": "forced", "initloc": {"y": 0, "x": 0}, "size": 21}, {"color": "#ff1035", "text": "refused", "initloc": {"y": 0, "x": 0}, "size": 20}, {"color": "#c66d7f", "text": "despite", "initloc": {"y": 0, "x": 0}, "size": 17}, {"color": "#ff3d4b", "text": "wives", "initloc": {"y": 0, "x": 0}, "size": 13}, {"color": "#ff3986", "text": "himself", "initloc": {"y": 0, "x": 0}, "size": 13}, {"color": "#c99874", "text": "against", "initloc": {"y": 0, "x": 0}, "size": 12}, {"color": "#ff3955", "text": "heir", "initloc": {"y": 0, "x": 0}, "size": 12}, {"color": "#ff2d78", "text": "refusing", "initloc": {"y": 0, "x": 0}, "size": 12}, {"color": "#d088a4", "text": "fights", "initloc": {"y": 0, "x": 0}, "size": 12}, {"color": "#bd6062", "text": "however", "initloc": {"y": 0, "x": 0}, "size": 12}, {"color": "#af3531", "text": "retire", "initloc": {"y": 0, "x": 0}, "size": 12}, {"color": "#f53bb0", "text": "unwilling", "initloc": {"y": 0, "x": 0}, "size": 12}, {"color": "#fa6373", "text": "slain", "initloc": {"y": 0, "x": 0}, "size": 11}, {"color": "#ff2945", "text": "children", "initloc": {"y": 0, "x": 0}, "size": 11}, {"color": "#e96da9", "text": "fight", "initloc": {"y": 0, "x": 0}, "size": 11}, {"color": "#95671d", "text": "occasions", "initloc": {"y": 0, "x": 0}, "size": 11}, {"color": "#ff1c3e", "text": "whom", "initloc": {"y": 0, "x": 0}, "size": 11}, {"color": "#ff3446", "text": "pleaded", "initloc": {"y": 0, "x": 0}, "size": 11}, {"color": "#da7d5c", "text": "men", "initloc": {"y": 0, "x": 0}, "size": 11}, {"color": "#ff0054", "text": "parents", "initloc": {"y": 0, "x": 0}, "size": 11}], "cb": 0, "zyx": [7, 46, 22]}