{"corr": -0.042674867358706771, "p": 0.76582793084877876, "rgb": "#4f7e98", "ncc_corr": -0.094535209823517499, "words": [{"color": "#038e86", "text": "lit", "initloc": {"y": 0, "x": 0}, "size": 6}, {"color": "#708eb6", "text": "leaning", "initloc": {"y": 0, "x": 0}, "size": 6}, {"color": "#878b71", "text": "naked", "initloc": {"y": 0, "x": 0}, "size": 5}, {"color": "#5845df", "text": "relaxed", "initloc": {"y": 0, "x": 0}, "size": 5}, {"color": "#2793db", "text": "warmth", "initloc": {"y": 0, "x": 0}, "size": 5}, {"color": "#818898", "text": "popped", "initloc": {"y": 0, "x": 0}, "size": 5}, {"color": "#30cc68", "text": "rolled", "initloc": {"y": 0, "x": 0}, "size": 5}, {"color": "#5775c7", "text": "motions", "initloc": {"y": 0, "x": 0}, "size": 4}, {"color": "#857785", "text": "jerked", "initloc": {"y": 0, "x": 0}, "size": 4}, {"color": "#6f8ea5", "text": "cue", "initloc": {"y": 0, "x": 0}, "size": 4}, {"color": "#4271bb", "text": "yoga", "initloc": {"y": 0, "x": 0}, "size": 4}, {"color": "#17df89", "text": "cube", "initloc": {"y": 0, "x": 0}, "size": 4}, {"color": "#5e65bf", "text": "rocked", "initloc": {"y": 0, "x": 0}, "size": 4}, {"color": "#10a81e", "text": "sports", "initloc": {"y": 0, "x": 0}, "size": 4}, {"color": "#43cc38", "text": "t-shirt", "initloc": {"y": 0, "x": 0}, "size": 4}, {"color": "#39b984", "text": "resting", "initloc": {"y": 0, "x": 0}, "size": 4}, {"color": "#581e5b", "text": "sat", "initloc": {"y": 0, "x": 0}, "size": 4}, {"color": "#5768bc", "text": "blew", "initloc": {"y": 0, "x": 0}, "size": 4}, {"color": "#3fc144", "text": "panel", "initloc": {"y": 0, "x": 0}, "size": 4}, {"color": "#5c41aa", "text": "staring", "initloc": {"y": 0, "x": 0}, "size": 4}], "cb": 0, "zyx": [7, 73, 38]}