{"corr": -0.018686749052867973, "p": 0.62454048074313084, "rgb": "#888e7d", "ncc_corr": -0.0066721277741441862, "words": [{"color": "#69393d", "text": "books", "initloc": {"y": 0, "x": 0}, "size": 15}, {"color": "#8f3367", "text": "book", "initloc": {"y": 0, "x": 0}, "size": 13}, {"color": "#4a825b", "text": "volumes", "initloc": {"y": 0, "x": 0}, "size": 13}, {"color": "#857a75", "text": "novels", "initloc": {"y": 0, "x": 0}, "size": 13}, {"color": "#9f4755", "text": "manuscript", "initloc": {"y": 0, "x": 0}, "size": 12}, {"color": "#7c7a58", "text": "published", "initloc": {"y": 0, "x": 0}, "size": 12}, {"color": "#57af6c", "text": "original", "initloc": {"y": 0, "x": 0}, "size": 11}, {"color": "#43b60d", "text": "printed", "initloc": {"y": 0, "x": 0}, "size": 11}, {"color": "#8b557e", "text": "poems", "initloc": {"y": 0, "x": 0}, "size": 9}, {"color": "#a27891", "text": "written", "initloc": {"y": 0, "x": 0}, "size": 9}, {"color": "#c535ad", "text": "wrote", "initloc": {"y": 0, "x": 0}, "size": 8}, {"color": "#b87b4a", "text": "robert", "initloc": {"y": 0, "x": 0}, "size": 8}, {"color": "#437d2d", "text": "photographs", "initloc": {"y": 0, "x": 0}, "size": 8}, {"color": "#516a49", "text": "pages", "initloc": {"y": 0, "x": 0}, "size": 8}, {"color": "#449c1e", "text": "printing", "initloc": {"y": 0, "x": 0}, "size": 8}, {"color": "#766222", "text": "newspapers", "initloc": {"y": 0, "x": 0}, "size": 8}, {"color": "#39ad2e", "text": "edition", "initloc": {"y": 0, "x": 0}, "size": 8}, {"color": "#48da5d", "text": "parchment", "initloc": {"y": 0, "x": 0}, "size": 8}, {"color": "#e15f57", "text": "mary", "initloc": {"y": 0, "x": 0}, "size": 7}, {"color": "#9c6f94", "text": "novel", "initloc": {"y": 0, "x": 0}, "size": 7}], "cb": 0, "zyx": [14, 85, 33]}