{"corr": 0.019536356733015212, "p": 0.36999651822664226, "rgb": "#6e53c6", "ncc_corr": -0.017973865815165226, "words": [{"color": "#61583d", "text": "together", "initloc": {"y": 0, "x": 0}, "size": 13}, {"color": "#a324d4", "text": "nightmare", "initloc": {"y": 0, "x": 0}, "size": 12}, {"color": "#b242ff", "text": "despair", "initloc": {"y": 0, "x": 0}, "size": 11}, {"color": "#8f3367", "text": "book", "initloc": {"y": 0, "x": 0}, "size": 10}, {"color": "#95008a", "text": "finally", "initloc": {"y": 0, "x": 0}, "size": 10}, {"color": "#8348b0", "text": "quest", "initloc": {"y": 0, "x": 0}, "size": 9}, {"color": "#8507f8", "text": "memories", "initloc": {"y": 0, "x": 0}, "size": 9}, {"color": "#60098e", "text": "journey", "initloc": {"y": 0, "x": 0}, "size": 9}, {"color": "#a06eed", "text": "mankind", "initloc": {"y": 0, "x": 0}, "size": 9}, {"color": "#7921cf", "text": "dream", "initloc": {"y": 0, "x": 0}, "size": 8}, {"color": "#ab58dc", "text": "forever", "initloc": {"y": 0, "x": 0}, "size": 8}, {"color": "#7c8fdc", "text": "magical", "initloc": {"y": 0, "x": 0}, "size": 8}, {"color": "#8565b8", "text": "trapped", "initloc": {"y": 0, "x": 0}, "size": 8}, {"color": "#bd21d4", "text": "haunt", "initloc": {"y": 0, "x": 0}, "size": 8}, {"color": "#556ec0", "text": "worlds", "initloc": {"y": 0, "x": 0}, "size": 8}, {"color": "#7671c4", "text": "abyss", "initloc": {"y": 0, "x": 0}, "size": 8}, {"color": "#47bf62", "text": "sealed", "initloc": {"y": 0, "x": 0}, "size": 8}, {"color": "#ff04d5", "text": "convinced", "initloc": {"y": 0, "x": 0}, "size": 8}, {"color": "#bc55ef", "text": "doomed", "initloc": {"y": 0, "x": 0}, "size": 8}, {"color": "#6379d0", "text": "glorious", "initloc": {"y": 0, "x": 0}, "size": 8}], "cb": 0, "zyx": [12, 39, 68]}