{"corr": -0.070360629507551342, "p": 0.88426484252673276, "rgb": "#417191", "ncc_corr": -0.12116666750674313, "words": [{"color": "#5a7cff", "text": "deepest", "initloc": {"y": 0, "x": 0}, "size": 10}, {"color": "#525add", "text": "cosmos", "initloc": {"y": 0, "x": 0}, "size": 9}, {"color": "#03a9ae", "text": "sky", "initloc": {"y": 0, "x": 0}, "size": 9}, {"color": "#6979d6", "text": "inspiration", "initloc": {"y": 0, "x": 0}, "size": 9}, {"color": "#618ab3", "text": "inspired", "initloc": {"y": 0, "x": 0}, "size": 9}, {"color": "#4d7b75", "text": "continues", "initloc": {"y": 0, "x": 0}, "size": 9}, {"color": "#2e7c53", "text": "www", "initloc": {"y": 0, "x": 0}, "size": 9}, {"color": "#617e36", "text": "children's", "initloc": {"y": 0, "x": 0}, "size": 8}, {"color": "#7921cf", "text": "dream", "initloc": {"y": 0, "x": 0}, "size": 8}, {"color": "#676853", "text": "disney", "initloc": {"y": 0, "x": 0}, "size": 8}, {"color": "#7397d7", "text": "beauty", "initloc": {"y": 0, "x": 0}, "size": 8}, {"color": "#6a88c9", "text": "glory", "initloc": {"y": 0, "x": 0}, "size": 8}, {"color": "#6e9e89", "text": "legends", "initloc": {"y": 0, "x": 0}, "size": 8}, {"color": "#723aff", "text": "awe", "initloc": {"y": 0, "x": 0}, "size": 8}, {"color": "#6b4af2", "text": "fascinated", "initloc": {"y": 0, "x": 0}, "size": 8}, {"color": "#51b36d", "text": "tulip", "initloc": {"y": 0, "x": 0}, "size": 8}, {"color": "#999bc2", "text": "fairy", "initloc": {"y": 0, "x": 0}, "size": 8}, {"color": "#a020a6", "text": "future", "initloc": {"y": 0, "x": 0}, "size": 8}, {"color": "#15d29f", "text": "rainbow", "initloc": {"y": 0, "x": 0}, "size": 8}, {"color": "#8821f4", "text": "dreams", "initloc": {"y": 0, "x": 0}, "size": 7}], "cb": 0, "zyx": [22, 67, 41]}