{"corr": 0.075224264105233876, "p": 0.10035693844446075, "rgb": "#90a589", "ncc_corr": 0.19509291494481512, "words": [{"color": "#87e76a", "text": "arms", "initloc": {"y": 0, "x": 0}, "size": 10}, {"color": "#4c7eb0", "text": "closer", "initloc": {"y": 0, "x": 0}, "size": 10}, {"color": "#3eff68", "text": "tail", "initloc": {"y": 0, "x": 0}, "size": 9}, {"color": "#628f88", "text": "flung", "initloc": {"y": 0, "x": 0}, "size": 9}, {"color": "#586e4f", "text": "standing", "initloc": {"y": 0, "x": 0}, "size": 9}, {"color": "#65ac5b", "text": "kneeling", "initloc": {"y": 0, "x": 0}, "size": 8}, {"color": "#89cc61", "text": "holding", "initloc": {"y": 0, "x": 0}, "size": 8}, {"color": "#59ff6b", "text": "legs", "initloc": {"y": 0, "x": 0}, "size": 8}, {"color": "#65ff81", "text": "neck", "initloc": {"y": 0, "x": 0}, "size": 8}, {"color": "#8fbaad", "text": "fists", "initloc": {"y": 0, "x": 0}, "size": 7}, {"color": "#58ff49", "text": "black", "initloc": {"y": 0, "x": 0}, "size": 7}, {"color": "#65ff80", "text": "symbol", "initloc": {"y": 0, "x": 0}, "size": 7}, {"color": "#81fc98", "text": "forehead", "initloc": {"y": 0, "x": 0}, "size": 7}, {"color": "#75c7a3", "text": "knees", "initloc": {"y": 0, "x": 0}, "size": 7}, {"color": "#639f83", "text": "swung", "initloc": {"y": 0, "x": 0}, "size": 7}, {"color": "#22f869", "text": "hole", "initloc": {"y": 0, "x": 0}, "size": 7}, {"color": "#58ff9d", "text": "belly", "initloc": {"y": 0, "x": 0}, "size": 7}, {"color": "#74f2d9", "text": "flaming", "initloc": {"y": 0, "x": 0}, "size": 7}, {"color": "#04ff6d", "text": "curved", "initloc": {"y": 0, "x": 0}, "size": 7}, {"color": "#60e375", "text": "heads", "initloc": {"y": 0, "x": 0}, "size": 7}], "cb": 0, "zyx": [13, 76, 35]}