{"corr": 0.10994324295410804, "p": 0.030527217527515044, "rgb": "#b0681f", "ncc_corr": 0.21683571182385414, "words": [{"color": "#cfad3d", "text": "female", "initloc": {"y": 0, "x": 0}, "size": 18}, {"color": "#ff0048", "text": "husband", "initloc": {"y": 0, "x": 0}, "size": 16}, {"color": "#e4c145", "text": "male", "initloc": {"y": 0, "x": 0}, "size": 15}, {"color": "#ff6167", "text": "woman", "initloc": {"y": 0, "x": 0}, "size": 15}, {"color": "#aa6559", "text": "girls", "initloc": {"y": 0, "x": 0}, "size": 14}, {"color": "#ff242b", "text": "married", "initloc": {"y": 0, "x": 0}, "size": 14}, {"color": "#ff3d4b", "text": "wives", "initloc": {"y": 0, "x": 0}, "size": 13}, {"color": "#ea0770", "text": "girlfriend", "initloc": {"y": 0, "x": 0}, "size": 13}, {"color": "#ff023e", "text": "wife", "initloc": {"y": 0, "x": 0}, "size": 13}, {"color": "#ff3661", "text": "husbands", "initloc": {"y": 0, "x": 0}, "size": 13}, {"color": "#bf005c", "text": "friends", "initloc": {"y": 0, "x": 0}, "size": 12}, {"color": "#f1047b", "text": "boyfriend", "initloc": {"y": 0, "x": 0}, "size": 12}, {"color": "#d43d2e", "text": "wedding", "initloc": {"y": 0, "x": 0}, "size": 12}, {"color": "#b13992", "text": "movie", "initloc": {"y": 0, "x": 0}, "size": 11}, {"color": "#ff0054", "text": "parents", "initloc": {"y": 0, "x": 0}, "size": 11}, {"color": "#8e4394", "text": "movies", "initloc": {"y": 0, "x": 0}, "size": 11}, {"color": "#e75478", "text": "girl", "initloc": {"y": 0, "x": 0}, "size": 11}, {"color": "#970144", "text": "roommates", "initloc": {"y": 0, "x": 0}, "size": 11}, {"color": "#a44353", "text": "closet", "initloc": {"y": 0, "x": 0}, "size": 10}, {"color": "#da5a2a", "text": "maid", "initloc": {"y": 0, "x": 0}, "size": 10}], "cb": 0, "zyx": [25, 32, 39]}