{"corr": 0.15942167355223202, "p": 0.0032123866926075805, "rgb": "#df8ee0", "ncc_corr": 0.30961824058614573, "words": [{"color": "#ff3ff3", "text": "dying", "initloc": {"y": 0, "x": 0}, "size": 30}, {"color": "#ff4ff2", "text": "tortured", "initloc": {"y": 0, "x": 0}, "size": 30}, {"color": "#ff5ed6", "text": "innocent", "initloc": {"y": 0, "x": 0}, "size": 30}, {"color": "#ff40f2", "text": "alive", "initloc": {"y": 0, "x": 0}, "size": 30}, {"color": "#ff34ff", "text": "believing", "initloc": {"y": 0, "x": 0}, "size": 30}, {"color": "#ff6ce4", "text": "die", "initloc": {"y": 0, "x": 0}, "size": 30}, {"color": "#ff61db", "text": "believed", "initloc": {"y": 0, "x": 0}, "size": 30}, {"color": "#ff68cc", "text": "killing", "initloc": {"y": 0, "x": 0}, "size": 30}, {"color": "#fb89ff", "text": "evil", "initloc": {"y": 0, "x": 0}, "size": 30}, {"color": "#ff6eff", "text": "cruel", "initloc": {"y": 0, "x": 0}, "size": 30}, {"color": "#ff52f3", "text": "believes", "initloc": {"y": 0, "x": 0}, "size": 30}, {"color": "#ff58b0", "text": "dies", "initloc": {"y": 0, "x": 0}, "size": 28}, {"color": "#fc42fd", "text": "suffering", "initloc": {"y": 0, "x": 0}, "size": 28}, {"color": "#c889e8", "text": "immortal", "initloc": {"y": 0, "x": 0}, "size": 28}, {"color": "#cfb1e1", "text": "deadly", "initloc": {"y": 0, "x": 0}, "size": 27}, {"color": "#ff3ca8", "text": "death", "initloc": {"y": 0, "x": 0}, "size": 27}, {"color": "#ff488f", "text": "murder", "initloc": {"y": 0, "x": 0}, "size": 26}, {"color": "#fa40f5", "text": "torment", "initloc": {"y": 0, "x": 0}, "size": 25}, {"color": "#ff2bc4", "text": "illness", "initloc": {"y": 0, "x": 0}, "size": 25}, {"color": "#ff8cd0", "text": "kills", "initloc": {"y": 0, "x": 0}, "size": 25}], "cb": 1, "zyx": [4, 44, 69]}