{"corr": 0.07473259649680826, "p": 0.10184052089303415, "rgb": "#462787", "ncc_corr": 0.15733840722474315, "words": [{"color": "#666f57", "text": "cleaned", "initloc": {"y": 0, "x": 0}, "size": 15}, {"color": "#3f8d5f", "text": "blankets", "initloc": {"y": 0, "x": 0}, "size": 14}, {"color": "#00c495", "text": "humidity", "initloc": {"y": 0, "x": 0}, "size": 13}, {"color": "#5c7e40", "text": "cleaning", "initloc": {"y": 0, "x": 0}, "size": 13}, {"color": "#0aac5b", "text": "electrical", "initloc": {"y": 0, "x": 0}, "size": 11}, {"color": "#21b09e", "text": "freezing", "initloc": {"y": 0, "x": 0}, "size": 11}, {"color": "#3d9861", "text": "bathing", "initloc": {"y": 0, "x": 0}, "size": 11}, {"color": "#243fbc", "text": "rumbling", "initloc": {"y": 0, "x": 0}, "size": 11}, {"color": "#6aa37e", "text": "bathed", "initloc": {"y": 0, "x": 0}, "size": 11}, {"color": "#03c4b1", "text": "warm", "initloc": {"y": 0, "x": 0}, "size": 10}, {"color": "#5958aa", "text": "drowsy", "initloc": {"y": 0, "x": 0}, "size": 10}, {"color": "#0fdb7f", "text": "damp", "initloc": {"y": 0, "x": 0}, "size": 10}, {"color": "#560f7f", "text": "nap", "initloc": {"y": 0, "x": 0}, "size": 10}, {"color": "#48ad36", "text": "towels", "initloc": {"y": 0, "x": 0}, "size": 10}, {"color": "#00a0a6", "text": "cloudy", "initloc": {"y": 0, "x": 0}, "size": 10}, {"color": "#438d47", "text": "bath", "initloc": {"y": 0, "x": 0}, "size": 9}, {"color": "#6ec4e2", "text": "mild", "initloc": {"y": 0, "x": 0}, "size": 9}, {"color": "#42996f", "text": "pillows", "initloc": {"y": 0, "x": 0}, "size": 9}, {"color": "#46d186", "text": "washed", "initloc": {"y": 0, "x": 0}, "size": 9}, {"color": "#9500b1", "text": "asleep", "initloc": {"y": 0, "x": 0}, "size": 9}], "cb": 0, "zyx": [14, 25, 41]}