{"corr": -0.033056138995053705, "p": 0.71281319576583002, "rgb": "#9f9e5b", "ncc_corr": -0.042537241559599419, "words": [{"color": "#96d758", "text": "males", "initloc": {"y": 0, "x": 0}, "size": 11}, {"color": "#91d257", "text": "females", "initloc": {"y": 0, "x": 0}, "size": 10}, {"color": "#60e375", "text": "heads", "initloc": {"y": 0, "x": 0}, "size": 8}, {"color": "#5eff76", "text": "necks", "initloc": {"y": 0, "x": 0}, "size": 8}, {"color": "#4dbc40", "text": "nest", "initloc": {"y": 0, "x": 0}, "size": 8}, {"color": "#e4c145", "text": "male", "initloc": {"y": 0, "x": 0}, "size": 7}, {"color": "#60ff68", "text": "tails", "initloc": {"y": 0, "x": 0}, "size": 7}, {"color": "#96989f", "text": "attractive", "initloc": {"y": 0, "x": 0}, "size": 7}, {"color": "#e48271", "text": "women", "initloc": {"y": 0, "x": 0}, "size": 7}, {"color": "#88984a", "text": "population", "initloc": {"y": 0, "x": 0}, "size": 7}, {"color": "#cfad3d", "text": "female", "initloc": {"y": 0, "x": 0}, "size": 7}, {"color": "#a3658b", "text": "adults", "initloc": {"y": 0, "x": 0}, "size": 6}, {"color": "#3ff677", "text": "erect", "initloc": {"y": 0, "x": 0}, "size": 6}, {"color": "#68ffce", "text": "stem", "initloc": {"y": 0, "x": 0}, "size": 6}, {"color": "#ac88b9", "text": "attracted", "initloc": {"y": 0, "x": 0}, "size": 6}, {"color": "#8caddb", "text": "mature", "initloc": {"y": 0, "x": 0}, "size": 6}, {"color": "#7e7805", "text": "seat", "initloc": {"y": 0, "x": 0}, "size": 6}, {"color": "#40ff46", "text": "trimmed", "initloc": {"y": 0, "x": 0}, "size": 5}, {"color": "#69e668", "text": "weigh", "initloc": {"y": 0, "x": 0}, "size": 5}, {"color": "#52ff99", "text": "hairs", "initloc": {"y": 0, "x": 0}, "size": 5}], "cb": 0, "zyx": [9, 22, 70]}