{"corr": 0.081117918790444318, "p": 0.083779846480074263, "rgb": "#8e72a0", "ncc_corr": 0.099007017949488504, "words": [{"color": "#6b7275", "text": "thousands", "initloc": {"y": 0, "x": 0}, "size": 21}, {"color": "#c15288", "text": "crisis", "initloc": {"y": 0, "x": 0}, "size": 20}, {"color": "#869d9d", "text": "millions", "initloc": {"y": 0, "x": 0}, "size": 19}, {"color": "#cf45f8", "text": "terror", "initloc": {"y": 0, "x": 0}, "size": 18}, {"color": "#786983", "text": "efforts", "initloc": {"y": 0, "x": 0}, "size": 18}, {"color": "#ff7190", "text": "victims", "initloc": {"y": 0, "x": 0}, "size": 15}, {"color": "#9436b0", "text": "continue", "initloc": {"y": 0, "x": 0}, "size": 15}, {"color": "#a53d6e", "text": "eventually", "initloc": {"y": 0, "x": 0}, "size": 15}, {"color": "#c3337a", "text": "urged", "initloc": {"y": 0, "x": 0}, "size": 14}, {"color": "#a35555", "text": "administration", "initloc": {"y": 0, "x": 0}, "size": 14}, {"color": "#cb615e", "text": "government", "initloc": {"y": 0, "x": 0}, "size": 14}, {"color": "#ff2f60", "text": "prison", "initloc": {"y": 0, "x": 0}, "size": 14}, {"color": "#b02ac6", "text": "panic", "initloc": {"y": 0, "x": 0}, "size": 14}, {"color": "#627ca8", "text": "collapse", "initloc": {"y": 0, "x": 0}, "size": 14}, {"color": "#b11394", "text": "unable", "initloc": {"y": 0, "x": 0}, "size": 14}, {"color": "#d81e4e", "text": "forced", "initloc": {"y": 0, "x": 0}, "size": 13}, {"color": "#ac70d4", "text": "destruction", "initloc": {"y": 0, "x": 0}, "size": 13}, {"color": "#6764bc", "text": "effort", "initloc": {"y": 0, "x": 0}, "size": 13}, {"color": "#bd6d60", "text": "congress", "initloc": {"y": 0, "x": 0}, "size": 13}, {"color": "#be4b92", "text": "attempt", "initloc": {"y": 0, "x": 0}, "size": 13}], "cb": 0, "zyx": [13, 12, 54]}