{"corr": 0.085785272097559193, "p": 0.072175154808461442, "rgb": "#70666d", "ncc_corr": 0.18004591572234632, "words": [{"color": "#4de09a", "text": "spin", "initloc": {"y": 0, "x": 0}, "size": 19}, {"color": "#7870aa", "text": "universes", "initloc": {"y": 0, "x": 0}, "size": 16}, {"color": "#5c68c8", "text": "quantum", "initloc": {"y": 0, "x": 0}, "size": 15}, {"color": "#29c07a", "text": "sub", "initloc": {"y": 0, "x": 0}, "size": 13}, {"color": "#5bb669", "text": "formula", "initloc": {"y": 0, "x": 0}, "size": 12}, {"color": "#32ff32", "text": "ball", "initloc": {"y": 0, "x": 0}, "size": 11}, {"color": "#424958", "text": "usual", "initloc": {"y": 0, "x": 0}, "size": 11}, {"color": "#646aa8", "text": "opposite", "initloc": {"y": 0, "x": 0}, "size": 11}, {"color": "#28cbb4", "text": "particles", "initloc": {"y": 0, "x": 0}, "size": 11}, {"color": "#987dcc", "text": "bang", "initloc": {"y": 0, "x": 0}, "size": 10}, {"color": "#4d3f82", "text": "math", "initloc": {"y": 0, "x": 0}, "size": 10}, {"color": "#7b708f", "text": "ra", "initloc": {"y": 0, "x": 0}, "size": 10}, {"color": "#c82e3b", "text": "party", "initloc": {"y": 0, "x": 0}, "size": 10}, {"color": "#6a75af", "text": "infinity", "initloc": {"y": 0, "x": 0}, "size": 10}, {"color": "#98707a", "text": "probability", "initloc": {"y": 0, "x": 0}, "size": 9}, {"color": "#34ba49", "text": "x", "initloc": {"y": 0, "x": 0}, "size": 9}, {"color": "#a35a6a", "text": "rules", "initloc": {"y": 0, "x": 0}, "size": 9}, {"color": "#2ed601", "text": "cup", "initloc": {"y": 0, "x": 0}, "size": 9}, {"color": "#8dc18b", "text": "equal", "initloc": {"y": 0, "x": 0}, "size": 9}, {"color": "#31b109", "text": "slot", "initloc": {"y": 0, "x": 0}, "size": 9}], "cb": 0, "zyx": [8, 25, 52]}