{"corr": 0.082820428166487742, "p": 0.079395138372828966, "rgb": "#6b607b", "ncc_corr": 0.11545008620510566, "words": [{"color": "#4b9446", "text": "scheme", "initloc": {"y": 0, "x": 0}, "size": 9}, {"color": "#795e7b", "text": "files", "initloc": {"y": 0, "x": 0}, "size": 9}, {"color": "#06c16f", "text": "lines", "initloc": {"y": 0, "x": 0}, "size": 8}, {"color": "#7a3f00", "text": "business", "initloc": {"y": 0, "x": 0}, "size": 8}, {"color": "#2c6e6f", "text": "data", "initloc": {"y": 0, "x": 0}, "size": 8}, {"color": "#25866f", "text": "channels", "initloc": {"y": 0, "x": 0}, "size": 8}, {"color": "#119e5d", "text": "engines", "initloc": {"y": 0, "x": 0}, "size": 7}, {"color": "#5f4792", "text": "links", "initloc": {"y": 0, "x": 0}, "size": 7}, {"color": "#1d782f", "text": "operating", "initloc": {"y": 0, "x": 0}, "size": 7}, {"color": "#2c3d61", "text": "computers", "initloc": {"y": 0, "x": 0}, "size": 7}, {"color": "#016369", "text": "windows", "initloc": {"y": 0, "x": 0}, "size": 7}, {"color": "#337140", "text": "operators", "initloc": {"y": 0, "x": 0}, "size": 7}, {"color": "#4d7e78", "text": "application", "initloc": {"y": 0, "x": 0}, "size": 7}, {"color": "#55ac2e", "text": "companies", "initloc": {"y": 0, "x": 0}, "size": 7}, {"color": "#bf1248", "text": "address", "initloc": {"y": 0, "x": 0}, "size": 7}, {"color": "#566876", "text": "code", "initloc": {"y": 0, "x": 0}, "size": 7}, {"color": "#9c259a", "text": "messages", "initloc": {"y": 0, "x": 0}, "size": 7}, {"color": "#984b23", "text": "financial", "initloc": {"y": 0, "x": 0}, "size": 7}, {"color": "#0cc550", "text": "diesel", "initloc": {"y": 0, "x": 0}, "size": 7}, {"color": "#0aab61", "text": "engine", "initloc": {"y": 0, "x": 0}, "size": 7}], "cb": 0, "zyx": [9, 25, 45]}