{"corr": 0.23018623943372257, "p": 3.6986690932454359e-05, "rgb": "#c7c7f5", "ncc_corr": 0.41804330739684165, "words": [{"color": "#e5aaff", "text": "vile", "initloc": {"y": 0, "x": 0}, "size": 30}, {"color": "#9cffde", "text": "flesh", "initloc": {"y": 0, "x": 0}, "size": 30}, {"color": "#bc98ce", "text": "thy", "initloc": {"y": 0, "x": 0}, "size": 30}, {"color": "#c45bff", "text": "gods", "initloc": {"y": 0, "x": 0}, "size": 30}, {"color": "#e698f2", "text": "cured", "initloc": {"y": 0, "x": 0}, "size": 30}, {"color": "#b193ff", "text": "humans", "initloc": {"y": 0, "x": 0}, "size": 30}, {"color": "#b977b6", "text": "ancestors", "initloc": {"y": 0, "x": 0}, "size": 30}, {"color": "#b854ff", "text": "eternal", "initloc": {"y": 0, "x": 0}, "size": 30}, {"color": "#e261da", "text": "christ", "initloc": {"y": 0, "x": 0}, "size": 30}, {"color": "#8cecd5", "text": "toxic", "initloc": {"y": 0, "x": 0}, "size": 30}, {"color": "#beafff", "text": "myth", "initloc": {"y": 0, "x": 0}, "size": 30}, {"color": "#cb4dff", "text": "misery", "initloc": {"y": 0, "x": 0}, "size": 30}, {"color": "#ff6ee1", "text": "jesus", "initloc": {"y": 0, "x": 0}, "size": 30}, {"color": "#8ce4d1", "text": "rot", "initloc": {"y": 0, "x": 0}, "size": 30}, {"color": "#f25ad0", "text": "sins", "initloc": {"y": 0, "x": 0}, "size": 30}, {"color": "#d39eff", "text": "cure", "initloc": {"y": 0, "x": 0}, "size": 30}, {"color": "#d59dff", "text": "human", "initloc": {"y": 0, "x": 0}, "size": 30}, {"color": "#be75e0", "text": "unto", "initloc": {"y": 0, "x": 0}, "size": 29}, {"color": "#c376cf", "text": "thee", "initloc": {"y": 0, "x": 0}, "size": 29}, {"color": "#49efc5", "text": "roots", "initloc": {"y": 0, "x": 0}, "size": 28}], "cb": 3, "zyx": [12, 44, 29]}