{"corr": -0.020471194620319131, "p": 0.63598446626532346, "rgb": "#8f8584", "ncc_corr": -0.011455050905465435, "words": [{"color": "#cd754f", "text": "queen", "initloc": {"y": 0, "x": 0}, "size": 5}, {"color": "#ff4a9c", "text": "sarah", "initloc": {"y": 0, "x": 0}, "size": 5}, {"color": "#7b708f", "text": "ra", "initloc": {"y": 0, "x": 0}, "size": 4}, {"color": "#95671d", "text": "occasions", "initloc": {"y": 0, "x": 0}, "size": 4}, {"color": "#29836f", "text": "curtains", "initloc": {"y": 0, "x": 0}, "size": 4}, {"color": "#610f1b", "text": "place", "initloc": {"y": 0, "x": 0}, "size": 3}, {"color": "#46caa6", "text": "flames", "initloc": {"y": 0, "x": 0}, "size": 3}, {"color": "#df615f", "text": "princess", "initloc": {"y": 0, "x": 0}, "size": 3}, {"color": "#92532e", "text": "ceremony", "initloc": {"y": 0, "x": 0}, "size": 3}, {"color": "#a9323f", "text": "occasion", "initloc": {"y": 0, "x": 0}, "size": 3}, {"color": "#e26059", "text": "bride", "initloc": {"y": 0, "x": 0}, "size": 3}, {"color": "#26ed80", "text": "sides", "initloc": {"y": 0, "x": 0}, "size": 2}, {"color": "#a49c66", "text": "pat", "initloc": {"y": 0, "x": 0}, "size": 2}, {"color": "#c78273", "text": "sean", "initloc": {"y": 0, "x": 0}, "size": 2}, {"color": "#7e6e9c", "text": "crowd", "initloc": {"y": 0, "x": 0}, "size": 2}, {"color": "#a76d42", "text": "captain", "initloc": {"y": 0, "x": 0}, "size": 2}, {"color": "#d43d2e", "text": "wedding", "initloc": {"y": 0, "x": 0}, "size": 2}, {"color": "#667347", "text": "whilst", "initloc": {"y": 0, "x": 0}, "size": 2}, {"color": "#a0898f", "text": "elf", "initloc": {"y": 0, "x": 0}, "size": 2}, {"color": "#58d378", "text": "roses", "initloc": {"y": 0, "x": 0}, "size": 2}], "cb": 0, "zyx": [10, 66, 57]}