{"tagproj": [{"color": "#b900ff", "tag": "mental", "value": 0.00086094521748350083}, {"color": "#ff3dff", "tag": "emotional", "value": -0.013262859798027996}, {"color": "#ff1264", "tag": "social", "value": -0.079493187281432134}, {"color": "#e56a6a", "tag": "communal", "value": -0.026150271881117518}, {"color": "#8c0000", "tag": "professional", "value": -0.052138735876188329}, {"color": "#fab9ff", "tag": "violent", "value": -0.013778496426099542}, {"color": "#3f060c", "tag": "temporal", "value": -0.0067707220745725676}, {"color": "#39e9ff", "tag": "abstract", "value": 0.065347727851398474}, {"color": "#008300", "tag": "locational", "value": 0.010946114609311953}, {"color": "#0fe000", "tag": "numeric", "value": 0.016799791705597804}, {"color": "#00ffaa", "tag": "tactile", "value": 0.065017189791095817}, {"color": "#14ff2d", "tag": "visual", "value": 0.030750482962673614}], "mean_ll_corr": 0.047697510362161848, "sfnr": 114.33667387318476, "mean_sem_corr": 0.12129589406980569, "rgb": "#10a0c0", "sig": 1, "words": [{"color": "#00ffb6", "text": "shapes", "initloc": {"y": 0, "x": 0}, "size": 30}, {"color": "#00bad0", "text": "depth", "initloc": {"y": 0, "x": 0}, "size": 30}, {"color": "#00ff9c", "text": "layers", "initloc": {"y": 0, "x": 0}, "size": 30}, {"color": "#00c9ac", "text": "patterns", "initloc": {"y": 0, "x": 0}, "size": 29}, {"color": "#0097db", "text": "clouds", "initloc": {"y": 0, "x": 0}, "size": 27}, {"color": "#03ffbb", "text": "dense", "initloc": {"y": 0, "x": 0}, "size": 26}, {"color": "#00dad6", "text": "intricate", "initloc": {"y": 0, "x": 0}, "size": 26}, {"color": "#00ffc3", "text": "smooth", "initloc": {"y": 0, "x": 0}, "size": 26}, {"color": "#0079d4", "text": "atmosphere", "initloc": {"y": 0, "x": 0}, "size": 26}, {"color": "#00ffaa", "text": "solid", "initloc": {"y": 0, "x": 0}, "size": 26}, {"color": "#00c495", "text": "humidity", "initloc": {"y": 0, "x": 0}, "size": 25}, {"color": "#00ff8e", "text": "surface", "initloc": {"y": 0, "x": 0}, "size": 25}, {"color": "#00ff94", "text": "layer", "initloc": {"y": 0, "x": 0}, "size": 24}, {"color": "#00db99", "text": "temperature", "initloc": {"y": 0, "x": 0}, "size": 24}, {"color": "#00ff73", "text": "edges", "initloc": {"y": 0, "x": 0}, "size": 24}, {"color": "#13a4e0", "text": "depths", "initloc": {"y": 0, "x": 0}, "size": 23}, {"color": "#27ff94", "text": "thinner", "initloc": {"y": 0, "x": 0}, "size": 22}, {"color": "#09ff96", "text": "thick", "initloc": {"y": 0, "x": 0}, "size": 22}, {"color": "#01ffc3", "text": "melting", "initloc": {"y": 0, "x": 0}, "size": 22}, {"color": "#24ffab", "text": "thicker", "initloc": {"y": 0, "x": 0}, "size": 21}], "label": "LPC R13"}